setup.py
proso/__init__.py
proso/geography/__init__.py
proso/geography/answers.py
proso/geography/answers_test.py
proso/geography/dfutil.py
proso/geography/places.py
proso/geography/places_test.py
proso_geography_data.egg-info/PKG-INFO
proso_geography_data.egg-info/SOURCES.txt
proso_geography_data.egg-info/dependency_links.txt
proso_geography_data.egg-info/namespace_packages.txt
proso_geography_data.egg-info/requires.txt
proso_geography_data.egg-info/top_level.txt