Metadata-Version: 1.0
Name: proso-geography-data
Version: 1.0.1
Summary: Libs for manipulation with data from PROSO Geography project
Home-page: https://github.com/proso/geography-data-libs/
Author: Jan Papousek
Author-email: jan.papousek@gmail.com
License: Gnu GPL v3
Platform: UNKNOWN
